{
"type": "FeatureCollection",
"name": "reserva",
"crs": { "type": "name", "properties": { "name": "urn:ogc:def:crs:OGC:1.3:CRS84" } },
"features": [
{ "type": "Feature", "properties": { "nro_fxb": null, "cta_min": "291", "cta_max": "300", "cable": "cc8" }, "geometry": { "type": "Point", "coordinates": [ -66.521707791846552, 10.467438376335151 ] } }
]
}
